setup.py
spidriver.py
spidriver.egg-info/PKG-INFO
spidriver.egg-info/SOURCES.txt
spidriver.egg-info/dependency_links.txt
spidriver.egg-info/requires.txt
spidriver.egg-info/top_level.txt