Metadata-Version: 1.2
Name: spidriver
Version: 1.0.0
Summary: SPIDriver is a desktop SPI interface
Home-page: https://spidriver.com
Author: James Bowman
Author-email: jamesb@excamera.com
License: GPL
Project-URL: Documentation, https://spidriver.readthedocs.io/en/latest/
Platform: UNKNOWN
